[
    {
      "id": 1,
      "image": "https://placehold.co/220x300",
      "categoryId": 1,
      "title": "1984",
      "authorId": 1,
      "shortDescription": "Dystopian classic",
      "description": "A chilling prophecy about the future.",
      "price": 15.99,
      "discountPrice": 12.99,
      "pageCount": 328,
      "status": "AVAILABLE",
      "createdAt": "2025-08-20T08:00:00Z",
      "updatedAt": "2025-08-20T08:00:00Z"
    },
    {
      "id": 2,
      "image": "https://placehold.co/220x300",
      "categoryId": 2,
      "title": "Harry Potter 1",
      "authorId": 2,
      "shortDescription": "Wizarding begins",
      "description": "The boy who lived.",
      "price": 20.99,
      "discountPrice": 18.99,
      "pageCount": 320,
      "status": "AVAILABLE",
      "createdAt": "2025-08-20T08:00:00Z",
      "updatedAt": "2025-08-20T08:00:00Z"
    },
    {
      "id": 3,
      "image": "https://placehold.co/220x300",
      "categoryId": 2,
      "title": "Harry Potter 2",
      "authorId": 2,
      "shortDescription": "Chamber secrets",
      "description": "The second year adventure.",
      "price": 21.99,
      "discountPrice": 19.49,
      "pageCount": 341,
      "status": "AVAILABLE",
      "createdAt": "2025-08-20T08:00:00Z",
      "updatedAt": "2025-08-20T08:00:00Z"
    },
    {
      "id": 4,
      "image": "https://placehold.co/220x300",
      "categoryId": 2,
      "title": "Harry Potter 3",
      "authorId": 2,
      "shortDescription": "Prisoner story",
      "description": "Sirius Black escapes.",
      "price": 22.99,
      "discountPrice": 20.49,
      "pageCount": 435,
      "status": "AVAILABLE",
      "createdAt": "2025-08-20T08:00:00Z",
      "updatedAt": "2025-08-20T08:00:00Z"
    },
    {
      "id": 5,
      "image": "https://placehold.co/220x300",
      "categoryId": 3,
      "title": "The Hobbit",
      "authorId": 3,
      "shortDescription": "Unexpected journey",
      "description": "Bilbo joins dwarves.",
      "price": 18.99,
      "discountPrice": 16.99,
      "pageCount": 310,
      "status": "AVAILABLE",
      "createdAt": "2025-08-20T08:00:00Z",
      "updatedAt": "2025-08-20T08:00:00Z"
    },
    {
      "id": 6,
      "image": "https://placehold.co/220x300",
      "categoryId": 2,
      "title": "LOTR Fellowship",
      "authorId": 3,
      "shortDescription": "Ring begins",
      "description": "Quest to destroy the One Ring.",
      "price": 25.99,
      "discountPrice": 22.99,
      "pageCount": 423,
      "status": "AVAILABLE",
      "createdAt": "2025-08-20T08:00:00Z",
      "updatedAt": "2025-08-20T08:00:00Z"
    },
    {
      "id": 7,
      "image": "https://placehold.co/220x300",
      "categoryId": 2,
      "title": "LOTR Two Towers",
      "authorId": 3,
      "shortDescription": "Middle journey",
      "description": "The fellowship splits.",
      "price": 26.99,
      "discountPrice": 23.49,
      "pageCount": 352,
      "status": "AVAILABLE",
      "createdAt": "2025-08-20T08:00:00Z",
      "updatedAt": "2025-08-20T08:00:00Z"
    },
    {
      "id": 8,
      "image": "https://placehold.co/220x300",
      "categoryId": 2,
      "title": "LOTR Return King",
      "authorId": 3,
      "shortDescription": "Final battle",
      "description": "The ring is destroyed.",
      "price": 28.99,
      "discountPrice": 24.99,
      "pageCount": 416,
      "status": "AVAILABLE",
      "createdAt": "2025-08-20T08:00:00Z",
      "updatedAt": "2025-08-20T08:00:00Z"
    },
    {
      "id": 9,
      "image": "https://placehold.co/220x300",
      "categoryId": 5,
      "title": "The Shining",
      "authorId": 4,
      "shortDescription": "Haunted hotel",
      "description": "Madness in isolation.",
      "price": 19.99,
      "discountPrice": 16.99,
      "pageCount": 447,
      "status": "AVAILABLE",
      "createdAt": "2025-08-20T08:00:00Z",
      "updatedAt": "2025-08-20T08:00:00Z"
    },
    {
      "id": 10,
      "image": "https://placehold.co/220x300",
      "categoryId": 5,
      "title": "IT",
      "authorId": 4,
      "shortDescription": "Evil clown",
      "description": "Derry’s terror resurfaces.",
      "price": 24.99,
      "discountPrice": 21.49,
      "pageCount": 1138,
      "status": "AVAILABLE",
      "createdAt": "2025-08-20T08:00:00Z",
      "updatedAt": "2025-08-20T08:00:00Z"
    },
    {
      "id": 11,
      "image": "https://placehold.co/220x300",
      "categoryId": 5,
      "title": "Carrie",
      "authorId": 4,
      "shortDescription": "Telekinetic girl",
      "description": "Tragedy at prom night.",
      "price": 14.99,
      "discountPrice": 12.49,
      "pageCount": 199,
      "status": "AVAILABLE",
      "createdAt": "2025-08-20T08:00:00Z",
      "updatedAt": "2025-08-20T08:00:00Z"
    },
    {
      "id": 12,
      "image": "https://placehold.co/220x300",
      "categoryId": 5,
      "title": "Misery",
      "authorId": 4,
      "shortDescription": "Obsession writer",
      "description": "A fan imprisons her idol.",
      "price": 17.99,
      "discountPrice": 15.49,
      "pageCount": 320,
      "status": "AVAILABLE",
      "createdAt": "2025-08-20T08:00:00Z",
      "updatedAt": "2025-08-20T08:00:00Z"
    },
    {
      "id": 13,
      "image": "https://placehold.co/220x300",
      "categoryId": 4,
      "title": "Murder Orient Express",
      "authorId": 5,
      "shortDescription": "Poirot mystery",
      "description": "Detective investigates train murder.",
      "price": 16.99,
      "discountPrice": 14.99,
      "pageCount": 256,
      "status": "AVAILABLE",
      "createdAt": "2025-08-20T08:00:00Z",
      "updatedAt": "2025-08-20T08:00:00Z"
    },
    {
      "id": 14,
      "image": "https://placehold.co/220x300",
      "categoryId": 4,
      "title": "Death Nile",
      "authorId": 5,
      "shortDescription": "Cruise murder",
      "description": "Murder during a Nile trip.",
      "price": 17.49,
      "discountPrice": 15.49,
      "pageCount": 288,
      "status": "AVAILABLE",
      "createdAt": "2025-08-20T08:00:00Z",
      "updatedAt": "2025-08-20T08:00:00Z"
    },
    {
      "id": 15,
      "image": "https://placehold.co/220x300",
      "categoryId": 4,
      "title": "And Then None",
      "authorId": 5,
      "shortDescription": "Isolated mystery",
      "description": "Ten strangers trapped.",
      "price": 18.49,
      "discountPrice": 16.49,
      "pageCount": 272,
      "status": "AVAILABLE",
      "createdAt": "2025-08-20T08:00:00Z",
      "updatedAt": "2025-08-20T08:00:00Z"
    },
    {
      "id": 16,
      "image": "https://placehold.co/220x300",
      "categoryId": 6,
      "title": "Long Walk Freedom",
      "authorId": 1,
      "shortDescription": "Mandela memoir",
      "description": "Autobiography of Nelson Mandela.",
      "price": 22.99,
      "discountPrice": 19.99,
      "pageCount": 656,
      "status": "AVAILABLE",
      "createdAt": "2025-08-20T08:00:00Z",
      "updatedAt": "2025-08-20T08:00:00Z"
    },
    {
      "id": 17,
      "image": "https://placehold.co/220x300",
      "categoryId": 7,
      "title": "World War II",
      "authorId": 3,
      "shortDescription": "Global conflict",
      "description": "History of WWII.",
      "price": 27.99,
      "discountPrice": 24.49,
      "pageCount": 784,
      "status": "AVAILABLE",
      "createdAt": "2025-08-20T08:00:00Z",
      "updatedAt": "2025-08-20T08:00:00Z"
    },
    {
      "id": 18,
      "image": "https://placehold.co/220x300",
      "categoryId": 7,
      "title": "Ancient Rome",
      "authorId": 5,
      "shortDescription": "Empire rise",
      "description": "History of Rome.",
      "price": 23.99,
      "discountPrice": 20.99,
      "pageCount": 512,
      "status": "AVAILABLE",
      "createdAt": "2025-08-20T08:00:00Z",
      "updatedAt": "2025-08-20T08:00:00Z"
    },
    {
      "id": 19,
      "image": "https://placehold.co/220x300",
      "categoryId": 1,
      "title": "Animal Farm",
      "authorId": 1,
      "shortDescription": "Satire animals",
      "description": "Political allegory.",
      "price": 14.49,
      "discountPrice": 12.49,
      "pageCount": 112,
      "status": "AVAILABLE",
      "createdAt": "2025-08-20T08:00:00Z",
      "updatedAt": "2025-08-20T08:00:00Z"
    },
    {
      "id": 20,
      "image": "https://placehold.co/220x300",
      "categoryId": 3,
      "title": "Foundation",
      "authorId": 2,
      "shortDescription": "Galactic saga",
      "description": "Sci-fi masterpiece.",
      "price": 19.49,
      "discountPrice": 17.49,
      "pageCount": 255,
      "status": "AVAILABLE",
      "createdAt": "2025-08-20T08:00:00Z",
      "updatedAt": "2025-08-20T08:00:00Z"
    }
]
